Kgmicolors/__init__.py
Kgmicolors/color_text.py
KgmiColors-0.1.1.dist-info/LICENCE
KgmiColors-0.1.1.dist-info/METADATA
KgmiColors-0.1.1.dist-info/WHEEL
KgmiColors-0.1.1.dist-info/top_level.txt
KgmiColors-0.1.1.dist-info/RECORD
