Metadata-Version: 2.2
Name: KgmiColors
Version: 0.1.1
Summary: Un package simple pour colorer les textes dans la console.
Home-page: https://github.com/Uwu-Kagami
Author: Kagami
Classifier: Programming Language :: Python :: 3
Classifier: License :: OSI Approved :: MIT License
Classifier: Operating System :: OS Independent
Requires-Python: >=3.6
License-File: LICENCE
Requires-Dist: requests<3.0.0,>=2.25.1
Dynamic: author
Dynamic: classifier
Dynamic: home-page
Dynamic: requires-dist
Dynamic: requires-python
Dynamic: summary
